EllipsePy/__init__.py
EllipsePy/bodies.py
EllipsePy/constants.py
EllipsePy/examples.py
EllipsePy/plotting.py
EllipsePy/utilities.py
EllipsePy-0.2.1.dist-info/LICENSE
EllipsePy-0.2.1.dist-info/METADATA
EllipsePy-0.2.1.dist-info/WHEEL
EllipsePy-0.2.1.dist-info/top_level.txt
EllipsePy-0.2.1.dist-info/RECORD
