Metadata-Version: 2.1
Name: EllipsePy
Version: 0.2.1
Summary: Orbital Mechanics Data Visualization and Analysis
Home-page: https://github.com/lalithu/EllipsePy
Author: Lalith Uriti
Author-email: lalithuriti@gmail.com
License: MIT
Platform: UNKNOWN
Classifier: Development Status :: 2 - Pre-Alpha
Classifier: Intended Audience :: Science/Research
Classifier: Programming Language :: Python :: 3
Classifier: License :: OSI Approved :: MIT License
Classifier: Topic :: Scientific/Engineering :: Astronomy
Requires-Dist: numpy
Requires-Dist: plotly
Requires-Dist: scipy
